guedo/__init__.py
guedo/dl.py
guedo_ee-0.1.1.dist-info/licenses/LICENSE
guedo_ee-0.1.1.dist-info/METADATA
guedo_ee-0.1.1.dist-info/WHEEL
guedo_ee-0.1.1.dist-info/top_level.txt
guedo_ee-0.1.1.dist-info/RECORD
